README.md
setup.cfg
setup.py
Heb/Heb.py
Heb/__init__.py
leandesk.egg-info/PKG-INFO
leandesk.egg-info/SOURCES.txt
leandesk.egg-info/dependency_links.txt
leandesk.egg-info/top_level.txt