Metadata-Version: 2.1
Name: leandesk
Version: 5.0.0
Summary: Clean your Directory with just one command
Author: Ibrahim
Author-email: string2025@gmail.com
